{
  "db_name": "PostgreSQL",
  "query": "\n            SELECT 1 AS \"1\"\n            FROM events\n            WHERE room_id = ANY($1)\n              AND origin_server_ts > $2\n            LIMIT 1\n            ",
  "describe": {
    "columns": [
      {
        "ordinal": 0,
        "name": "1",
        "type_info": "Int4"
      }
    ],
    "parameters": {
      "Left": [
        "TextArray",
        "Int8"
      ]
    },
    "nullable": [
      null
    ]
  },
  "hash": "57f6c226297d5ca36ecc67849af602a37cedef19387558cb4e44f4df62126791"
}
