{
  "db_name": "PostgreSQL",
  "query": "\n            INSERT INTO room_account_data (user_id, room_id, data_type, data, created_ts, updated_ts)\n            VALUES ($1, $2, $3, $4, $5, $5)\n            ON CONFLICT (user_id, room_id, data_type) DO UPDATE SET data = EXCLUDED.data, updated_ts = EXCLUDED.updated_ts\n            ",
  "describe": {
    "columns": [],
    "parameters": {
      "Left": [
        "Text",
        "Text",
        "Text",
        "Jsonb",
        "Int8"
      ]
    },
    "nullable": []
  },
  "hash": "9d233d17b29e50947d86c44900a5e8ac13d878fc5ddb4867b7be7afb0b142adb"
}
