{
  "db_name": "PostgreSQL",
  "query": "INSERT INTO widgets (widget_id, room_id, user_id, widget_type, url, name, data, created_ts, is_active)\n            VALUES ($1, $2, $3, $4, $5, $6, $7, $8, TRUE)\n            RETURNING id, widget_id, room_id, user_id, widget_type, url, name, data,\n                created_ts AS \"created_ts!\", updated_ts, is_active AS \"is_active!\"\n            ",
  "describe": {
    "columns": [
      {
        "ordinal": 0,
        "name": "id",
        "type_info": "Int8"
      },
      {
        "ordinal": 1,
        "name": "widget_id",
        "type_info": "Text"
      },
      {
        "ordinal": 2,
        "name": "room_id",
        "type_info": "Text"
      },
      {
        "ordinal": 3,
        "name": "user_id",
        "type_info": "Text"
      },
      {
        "ordinal": 4,
        "name": "widget_type",
        "type_info": "Text"
      },
      {
        "ordinal": 5,
        "name": "url",
        "type_info": "Text"
      },
      {
        "ordinal": 6,
        "name": "name",
        "type_info": "Text"
      },
      {
        "ordinal": 7,
        "name": "data",
        "type_info": "Jsonb"
      },
      {
        "ordinal": 8,
        "name": "created_ts!",
        "type_info": "Int8"
      },
      {
        "ordinal": 9,
        "name": "updated_ts",
        "type_info": "Int8"
      },
      {
        "ordinal": 10,
        "name": "is_active!",
        "type_info": "Bool"
      }
    ],
    "parameters": {
      "Left": [
        "Text",
        "Text",
        "Text",
        "Text",
        "Text",
        "Text",
        "Jsonb",
        "Int8"
      ]
    },
    "nullable": [
      false,
      false,
      true,
      false,
      false,
      false,
      false,
      false,
      false,
      true,
      false
    ]
  },
  "hash": "91a74a3c7460c7dd762f45f04f6b8267f284ff7ab897d97b84a16667bc77f130"
}
