{
  "db_name": "PostgreSQL",
  "query": "\n            INSERT INTO rooms (room_id, creator, join_rule, version, is_public, member_count, history_visibility, creation_ts, last_activity_ts)\n            VALUES ($1, $2, $3, $4, $5, 1, 'joined', $6, $7)\n            ",
  "describe": {
    "columns": [],
    "parameters": {
      "Left": [
        "Varchar",
        "Varchar",
        "Varchar",
        "Varchar",
        "Bool",
        "Int8",
        "Int8"
      ]
    },
    "nullable": []
  },
  "hash": "8edf0c14c0eb00c776d7b7a90000f7e5a5d00b0f0f86e0872fdb36ae483a4666"
}
