{
  "db_name": "PostgreSQL",
  "query": "SELECT media_id, content_type, file_name, size, uploader_user_id, created_ts,\n               NULL::BIGINT AS \"last_accessed_at?\", NULL::TEXT AS \"quarantine_status?\"\n               FROM media_metadata WHERE uploader_user_id = $1 ORDER BY created_ts DESC",
  "describe": {
    "columns": [
      {
        "ordinal": 0,
        "name": "media_id",
        "type_info": "Text"
      },
      {
        "ordinal": 1,
        "name": "content_type",
        "type_info": "Text"
      },
      {
        "ordinal": 2,
        "name": "file_name",
        "type_info": "Text"
      },
      {
        "ordinal": 3,
        "name": "size",
        "type_info": "Int8"
      },
      {
        "ordinal": 4,
        "name": "uploader_user_id",
        "type_info": "Text"
      },
      {
        "ordinal": 5,
        "name": "created_ts",
        "type_info": "Int8"
      },
      {
        "ordinal": 6,
        "name": "last_accessed_at?",
        "type_info": "Int8"
      },
      {
        "ordinal": 7,
        "name": "quarantine_status?",
        "type_info": "Text"
      }
    ],
    "parameters": {
      "Left": [
        "Text"
      ]
    },
    "nullable": [
      false,
      false,
      true,
      false,
      true,
      false,
      null,
      null
    ]
  },
  "hash": "bd08c9225b7c78e32bd9a45f2cf38495331ce4fac2fc3dd891e3f777f46c0ff1"
}
