{
  "db_name": "PostgreSQL",
  "query": "\n            SELECT device_id, user_id, display_name, device_key, last_seen_ts, last_seen_ip, created_at, first_seen_ts, created_ts, appservice_id, ignored_user_list\n            FROM devices WHERE user_id = $1 ORDER BY last_seen_ts DESC\n            ",
  "describe": {
    "columns": [
      {
        "ordinal": 0,
        "name": "device_id",
        "type_info": "Varchar"
      },
      {
        "ordinal": 1,
        "name": "user_id",
        "type_info": "Varchar"
      },
      {
        "ordinal": 2,
        "name": "display_name",
        "type_info": "Varchar"
      },
      {
        "ordinal": 3,
        "name": "device_key",
        "type_info": "Jsonb"
      },
      {
        "ordinal": 4,
        "name": "last_seen_ts",
        "type_info": "Int8"
      },
      {
        "ordinal": 5,
        "name": "last_seen_ip",
        "type_info": "Varchar"
      },
      {
        "ordinal": 6,
        "name": "created_at",
        "type_info": "Int8"
      },
      {
        "ordinal": 7,
        "name": "first_seen_ts",
        "type_info": "Int8"
      },
      {
        "ordinal": 8,
        "name": "created_ts",
        "type_info": "Int8"
      },
      {
        "ordinal": 9,
        "name": "appservice_id",
        "type_info": "Varchar"
      },
      {
        "ordinal": 10,
        "name": "ignored_user_list",
        "type_info": "Text"
      }
    ],
    "parameters": {
      "Left": [
        "Text"
      ]
    },
    "nullable": [
      false,
      false,
      true,
      true,
      true,
      true,
      false,
      false,
      true,
      true,
      true
    ]
  },
  "hash": "25eb00136ec738590bf497467147a5101aa7f2bed2f6acf8c26b003e339f1196"
}
