{
  "db_name": "PostgreSQL",
  "query": "\n            INSERT INTO user_privacy_settings (\n                user_id, profile_visibility, avatar_visibility, displayname_visibility,\n                presence_visibility, room_membership_visibility, created_ts, updated_ts\n            )\n            VALUES ($1, $2, $3, $4, $5, $6, $7, $8)\n            ON CONFLICT (user_id) DO UPDATE SET updated_ts = $8\n            RETURNING id as \"id!\", user_id as \"user_id!\", profile_visibility as \"profile_visibility!\", avatar_visibility as \"avatar_visibility!\", displayname_visibility as \"displayname_visibility!\", presence_visibility as \"presence_visibility!\", room_membership_visibility as \"room_membership_visibility!\", created_ts as \"created_ts!\", updated_ts as \"updated_ts!\"\n            ",
  "describe": {
    "columns": [
      {
        "ordinal": 0,
        "name": "id!",
        "type_info": "Int8"
      },
      {
        "ordinal": 1,
        "name": "user_id!",
        "type_info": "Varchar"
      },
      {
        "ordinal": 2,
        "name": "profile_visibility!",
        "type_info": "Text"
      },
      {
        "ordinal": 3,
        "name": "avatar_visibility!",
        "type_info": "Text"
      },
      {
        "ordinal": 4,
        "name": "displayname_visibility!",
        "type_info": "Text"
      },
      {
        "ordinal": 5,
        "name": "presence_visibility!",
        "type_info": "Text"
      },
      {
        "ordinal": 6,
        "name": "room_membership_visibility!",
        "type_info": "Text"
      },
      {
        "ordinal": 7,
        "name": "created_ts!",
        "type_info": "Int8"
      },
      {
        "ordinal": 8,
        "name": "updated_ts!",
        "type_info": "Int8"
      }
    ],
    "parameters": {
      "Left": [
        "Varchar",
        "Text",
        "Text",
        "Text",
        "Text",
        "Text",
        "Int8",
        "Int8"
      ]
    },
    "nullable": [
      false,
      false,
      false,
      false,
      false,
      false,
      false,
      false,
      true
    ]
  },
  "hash": "6301daffc5fa1ef836f5d27ed920710d84b4d0a435cf82f5420de04c695b510e"
}
